{"PalabrasReservadas":[{"Token":"PR01","Lexema":"CONDITION","TipoDeLexema":"Palabra Reservada"},{"Token":"PR02","Lexema":"OTHERWISE","TipoDeLexema":"Palabra Reservada"},{"Token":"PR03","Lexema":"LOOP","TipoDeLexema":"Palabra Reservada"},{"Token":"PR04","Lexema":"WHILST","TipoDeLexema":"Palabra Reservada"},{"Token":"PR05","Lexema":"PERFORM","TipoDeLexema":"Palabra Reservada"},{"Token":"PR06","Lexema":"SELECT","TipoDeLexema":"Palabra Reservada"},{"Token":"PR07","Lexema":"SENDBACK","TipoDeLexema":"Palabra Reservada"},{"Token":"PR08","Lexema":"STOP","TipoDeLexema":"Palabra Reservada"},{"Token":"PR09","Lexema":"OPTION","TipoDeLexema":"Palabra Reservada"},{"Token":"PR10","Lexema":"STANDARD","TipoDeLexema":"Palabra Reservada"},{"Token":"PR11","Lexema":"PROCEED","TipoDeLexema":"Palabra Reservada"},{"Token":"PR12","Lexema":"OPEN","TipoDeLexema":"Palabra Reservada"},{"Token":"PR13","Lexema":"CLOSED","TipoDeLexema":"Palabra Reservada"},{"Token":"PR14","Lexema":"SECURE","TipoDeLexema":"Palabra Reservada"},{"Token":"PR15","Lexema":"FIXED","TipoDeLexema":"Palabra Reservada"},{"Token":"CAP01","Lexema":"CAPTURE","TipoDeLexema":"Palabra Reservada"},{"Token":"PR16","Lexema":"INICIO","TipoDeLexema":"Palabra Reservada"},{"Token":"PR17","Lexema":"FIN","TipoDeLexema":"Palabra Reservada"}],"TiposDeDatos":[{"Token":"TPD01","Lexema":"INTEGER","TipoDeLexema":"Tipo De Dato"},{"Token":"TPD02","Lexema":"DECIMAL","TipoDeLexema":"Tipo De Dato"},{"Token":"TPD03","Lexema":"BOOLEAN","TipoDeLexema":"Tipo De Dato"},{"Token":"TPD04","Lexema":"TEXT","TipoDeLexema":"Tipo De Dato"},{"Token":"TPD05","Lexema":"CHAR","TipoDeLexema":"Tipo De Dato"}],"OperadoresAritmeticos":[{"Token":"OA01","Lexema":"\u002B","TipoDeLexema":"Operador Aritmetico"},{"Token":"OA02","Lexema":"-","TipoDeLexema":"Operador Aritmetico"},{"Token":"OA03","Lexema":"*","TipoDeLexema":"Operador Aritmetico"},{"Token":"OA04","Lexema":"/","TipoDeLexema":"Operador Aritmetico"},{"Token":"OA05","Lexema":"%","TipoDeLexema":"Operador Aritmetico"},{"Token":"OA06","Lexema":"\u002B\u002B","TipoDeLexema":"Operador Aritmetico"},{"Token":"OA07","Lexema":"--","TipoDeLexema":"Operador Aritmetico"}],"OperadoresLogicos":[{"Token":"OL01","Lexema":"\u0026\u0026","TipoDeLexema":"Operador Logico"},{"Token":"OL02","Lexema":"||","TipoDeLexema":"Operador Logico"},{"Token":"OL03","Lexema":"!","TipoDeLexema":"Operador Logico"}],"OperadoresRelacionales":[{"Token":"OR01","Lexema":"==","TipoDeLexema":"Operador Relacional"},{"Token":"OR02","Lexema":"!=","TipoDeLexema":"Operador Relacional"},{"Token":"OR03","Lexema":"\u003E","TipoDeLexema":"Operador Relacional"},{"Token":"OR04","Lexema":"\u003C","TipoDeLexema":"Operador Relacional"},{"Token":"OR05","Lexema":"\u003E=","TipoDeLexema":"Operador Relacional"},{"Token":"OR06","Lexema":"\u003C=","TipoDeLexema":"Operador Relacional"}],"Letreros":[{"Token":"LT01","Lexema":"DISPLAY","TipoDeLexema":"Letrero"}],"Comentarios":[{"Token":"CMT01","Lexema":"\u00AC","TipoDeLexema":"Comentario"},{"Token":"CMT02","Lexema":"\u00AC\u00AC","TipoDeLexema":"Comentario"}],"CaracteresEspeciales":[{"Token":"CE01","Lexema":"#","TipoDeLexema":"Caracter Especial"},{"Token":"CE02","Lexema":"$","TipoDeLexema":"Caracter Especial"},{"Token":"CE03","Lexema":".","TipoDeLexema":"Caracter Especial"},{"Token":"CE04","Lexema":"\\","TipoDeLexema":"Caracter Especial"},{"Token":"CE05","Lexema":"(","TipoDeLexema":"Caracter Especial"},{"Token":"CE06","Lexema":")","TipoDeLexema":"Caracter Especial"},{"Token":"CE07","Lexema":"=","TipoDeLexema":"Caracter Especial"},{"Token":"CE08","Lexema":"{","TipoDeLexema":"Caracter Especial"},{"Token":"CE09","Lexema":"}","TipoDeLexema":"Caracter Especial"},{"Token":"CE10","Lexema":"\u0022","TipoDeLexema":"Caracter Especial"},{"Token":"CE11","Lexema":";","TipoDeLexema":"Caracter Especial"},{"Token":"CE12","Lexema":":","TipoDeLexema":"Caracter Especial"},{"Token":"CE13","Lexema":"\u0027","TipoDeLexema":"Caracter Especial"}],"Variables":[{"Token":"VAR1","TipoDeLexema":"Variable"},{"Token":"VAR2","TipoDeLexema":"Variable"},{"Token":"VAR3","TipoDeLexema":"Variable"},{"Token":"VAR4","TipoDeLexema":"Variable"},{"Token":"VAR5","TipoDeLexema":"Variable"}],"Coeficientes":[{"Token":"COE1","TipoDeLexema":"Coeficiente"}],"Identificadores":[{"Token":"ID01","TipoDeLexema":"Identificador"}],"ValoresBooleanos":[{"Token":"BL01","Lexema":"TRUTH","TipoDeLexema":"Valor Booleano"},{"Token":"BL02","Lexema":"UNTRUTH","TipoDeLexema":"Valor Booleano"}],"ContenidoDeCadenas":[{"Token":"CD01","TipoDeLexema":"Cadena"}],"ContenidoDeCaracteres":[{"Token":"CR01","TipoDeLexema":"Caracter"}],"ContenidoDeComentarios":[{"Token":"CCT01","TipoDeLexema":"Contenido De Comentario"}],"Nulos":[{"Token":"NL01","Lexema":"NIL","TipoDeLexema":"Nulo"}]}